{
	"userInfo": {
		"userId": "EX1992",
		"userName": "zzh",
		"userlevel": "2",
		"cardInfo": [123123,45345,3567365]
	},
	"cardInfo": {
		"bus_count": 100,	
		"subway_count":40,	
		"park_count":10,
		"ride_time":86,	
		"ride_km":1412,	
		"westlake_round":6,
		"fitness_count":32,	
		"fitness_time":242,
		"save_electricity":56.31,	
		"online_recharge_count":4,
		"online_recharge_money":350,
		"medical_count":2,
		"inter_room_settlement":5,
		"save_wait_time":0,
		"cost_money":12318.12,
		"save_money":412.76,
		"bus_cost":100.54,
		"subway_cost":45.20,
		"park_cost":10.15,
		"save_co2":6524,
		"save_rank":86
	}
}